tokengeex-1.1.0.dist-info/METADATA
tokengeex-1.1.0.dist-info/WHEEL
tokengeex/__init__.py
tokengeex/__init__.pyi
tokengeex/py.typed
tokengeex/tokengeex.cp39-win32.pyd
tokengeex-1.1.0.dist-info/RECORD
