Metadata-Version: 2.3
Name: tokengeex
Version: 1.1.0
Classifier: Programming Language :: Rust
Classifier: Programming Language :: Python :: Implementation :: CPython
Classifier: Programming Language :: Python :: Implementation :: PyPy
Summary: TokenGeeX is an efficient tokenizer for code based on UnigramLM and TokenMonster.
Keywords: tokenizer,nlp
Home-Page: https://codegeex.cn
Author: Diego ROJAS (罗杰斯) <rojasdiegopro@gmail.com>
Author-email: "Diego ROJAS (罗杰斯)" <rojasdiegopro@gmail.com>
License: Apache-2.0
Requires-Python: >=3.8
Project-URL: Homepage, https://github.com/rojas-diego/tokengeex
Project-URL: Source, https://github.com/rojas-diego/tokengeex
